refseq_plasmid_dl/__init__.py
refseq_plasmid_dl/cli.py
refseq_plasmid_dl/downloader.py
refseq_plasmid_dl/processor.py
refseq_plasmid_dl-0.1.0.dist-info/licenses/LICENSE
refseq_plasmid_dl-0.1.0.dist-info/METADATA
refseq_plasmid_dl-0.1.0.dist-info/WHEEL
refseq_plasmid_dl-0.1.0.dist-info/entry_points.txt
refseq_plasmid_dl-0.1.0.dist-info/top_level.txt
refseq_plasmid_dl-0.1.0.dist-info/RECORD
