Metadata-Version: 2.4
Name: refseq-plasmid-dl
Version: 0.1.0
Summary: A command-line tool to download and curate RefSeq plasmid sequences from NCBI.
Author-email: Erin Young <eriny@utah.gov>
License:                     GNU GENERAL PUBLIC LICENSE
Project-URL: Homepage, https://github.com/erinyoung/refseq-plasmid-dl
Project-URL: Bug Tracker, https://github.com/erinyoung/refseq-plasmid-dl/issues
Keywords: bioinformatics,ncbi,plasmid,refseq,genomics
Classifier: Development Status :: 3 - Alpha
Classifier: Intended Audience :: Science/Research
Classifier: Programming Language :: Python :: 3
Classifier: Topic :: Scientific/Engineering :: Bio-Informatics
Classifier: Operating System :: OS Independent
Requires-Python: >=3.9
License-File: LICENSE
Requires-Dist: requests
Requires-Dist: beautifulsoup4
Requires-Dist: tqdm
Requires-Dist: biopython
Dynamic: license-file
